chatclouds/__init__.py
chatclouds-0.0.5.dist-info/LICENSE.txt
chatclouds-0.0.5.dist-info/METADATA
chatclouds-0.0.5.dist-info/WHEEL
chatclouds-0.0.5.dist-info/top_level.txt
chatclouds-0.0.5.dist-info/RECORD
