Metadata-Version: 2.1
Name: chatclouds
Version: 0.0.5
Summary: Allows you to make wordclouds for your Whatsapp Chats
Home-page: https://github.com/ishantjuyal/chatcloud
Author: Ishant Juyal
Author-email: ishantnit@gmail.com
License: MIT
Keywords: wordcloud
Platform: UNKNOWN
Classifier: Development Status :: 5 - Production/Stable
Classifier: Intended Audience :: Education
Classifier: Operating System :: Microsoft :: Windows :: Windows 10
Classifier: License :: OSI Approved :: MIT License
Classifier: Programming Language :: Python :: 3
Requires-Dist: wordcloud
Requires-Dist: matplotlib
Requires-Dist: pandas
Requires-Dist: contractions
